crypto_functions/__init__.py
crypto_functions/core.py
crypto_functions-1.0.0.dist-info/licenses/LICENSE.txt
crypto_functions-1.0.0.dist-info/METADATA
crypto_functions-1.0.0.dist-info/WHEEL
crypto_functions-1.0.0.dist-info/top_level.txt
crypto_functions-1.0.0.dist-info/RECORD
