Metadata-Version: 2.4
Name: crypto-functions
Version: 1.0.0
Summary: A simple and secure Python module for hashing and encrypting data and files.
Author-email: Anish Sethi <sethi.dynasty123@gmail.com>
License: MIT
Project-URL: Homepage, https://github.com/Anish-Sethi-12122/Crypto-Tools
Project-URL: Repository, https://github.com/Anish-Sethi-12122/Crypto-Tools
Requires-Python: >=3.8
License-File: LICENSE.txt
Requires-Dist: cryptography>=42.0.0
Requires-Dist: argon2-cffi>=23.1.0
Dynamic: license-file
